getharvest_api_wrapper/__init__.py
getharvest_api_wrapper/harvest_api.py
getharvest_api_wrapper-0.1.1.dist-info/LICENSE
getharvest_api_wrapper-0.1.1.dist-info/METADATA
getharvest_api_wrapper-0.1.1.dist-info/WHEEL
getharvest_api_wrapper-0.1.1.dist-info/top_level.txt
getharvest_api_wrapper-0.1.1.dist-info/RECORD
