Metadata-Version: 2.1
Name: getharvest-api-wrapper
Version: 0.1.1
Summary: A very basic and incomplete API Wrapper for the getharvest.com API
Home-page: https://gitlab.com/mrshll1001/python-harvest-api-wrapper/
Author: Matt Marshall
Author-email: communications@mrshll.uk
License: GPLv3
Platform: UNKNOWN
Classifier: Intended Audience :: Developers
Classifier: License :: OSI Approved :: GNU General Public License v3 (GPLv3)
Classifier: Programming Language :: Python
Classifier: Programming Language :: Python :: 3
Classifier: Operating System :: OS Independent
